eizo-0.3.0.dist-info/METADATA
eizo-0.3.0.dist-info/WHEEL
eizo/io.pyi
eizo/__init__.py
eizo/__init__.pyi
eizo/eizo.cp312-win_amd64.pyd
eizo-0.3.0.dist-info/RECORD
