Metadata-Version: 2.4
Name: eizo
Version: 0.3.0
Requires-Dist: numpy>2
Requires-Python: >=3.12
